jpt/.version
jpt/__init__.py
jpt/mlflow_wrapper.py
jpt/sequential_trees.py
jpt/trees.py
jpt/variables.py
jpt/version.py
jpt/base/__init__.py
jpt/base/constants.py
jpt/base/cutils.cpp
jpt/base/cutils.cpython-312-x86_64-linux-gnu.so
jpt/base/cutils.pyx
jpt/base/errors.py
jpt/base/functions.cpp
jpt/base/functions.cpython-312-x86_64-linux-gnu.so
jpt/base/functions.pyx
jpt/base/intervals.cpp
jpt/base/intervals.cpython-312-x86_64-linux-gnu.so
jpt/base/intervals.pyx
jpt/base/sampling.py
jpt/base/utils.py
jpt/distributions/__init__.py
jpt/distributions/multivariate.py
jpt/distributions/utils.py
jpt/distributions/quantile/__init__.py
jpt/distributions/quantile/cdfreg.cpp
jpt/distributions/quantile/cdfreg.cpython-312-x86_64-linux-gnu.so
jpt/distributions/quantile/cdfreg.pyx
jpt/distributions/quantile/quantiles.cpp
jpt/distributions/quantile/quantiles.cpython-312-x86_64-linux-gnu.so
jpt/distributions/quantile/quantiles.pyx
jpt/distributions/univariate/__init__.py
jpt/distributions/univariate/distribution.py
jpt/distributions/univariate/gaussian.py
jpt/distributions/univariate/integer.py
jpt/distributions/univariate/multinomial.py
jpt/distributions/univariate/numeric.py
jpt/inference/__init__.py
jpt/inference/mpe.py
jpt/learning/__init__.py
jpt/learning/impurity.cpp
jpt/learning/impurity.cpython-312-x86_64-linux-gnu.so
jpt/learning/impurity.pyx
pyjpt-0.1.41.dist-info/METADATA
pyjpt-0.1.41.dist-info/WHEEL
pyjpt-0.1.41.dist-info/top_level.txt
pyjpt-0.1.41.dist-info/RECORD
