Metadata-Version: 2.4
Name: pyjpt
Version: 0.1.41
Summary: Joint Probability Trees (short JPTs) are a formalism for learning of and reasoning about joint probability
License-Expression: MIT
Requires-Python: >=3.7
Provides-Extra: mlflow
Requires-Dist: mlflow>=2.5.0; extra == "mlflow"
